{
  "className":"com.globaltcad.swingtree.common.Basic_UI_Exception_Spec",
  "title":"",
  "narrative":"",
  "subjects":[],
  "statistics":{
    "runs":"1",
    "successRate":"100.0%",
    "failures":"0",
    "errors":"0",
    "skipped":"0",
    "duration":"0.055 seconds"
  },
  "headers":[],"tags":{},"see":[],
  "features":[ 
    {
      "id":"The given factory methods do not accept null arguments.",
      "result":"PASS",
      "duration":"0.014 seconds",
      "iterations":{
      "tags":{},"see":[],"extraInfo":[]
      },
      "blocks":[
        {"kind":"when","text":"We execute the error prone code...","code":["illegalAction()"]},

        {"kind":"then","text":"An illegal argument exception will be thrown!","code":["thrown(IllegalArgumentException)"]},

        {"kind":"where","text":"","code":{"illegalAction":["com.globaltcad.swingtree.common.Basic_UI_Exception_Spec$__spock_feature_0_0prov0_closure1@3311711e","com.globaltcad.swingtree.common.Basic_UI_Exception_Spec$__spock_feature_0_0prov0_closure2@4ee34dd4","com.globaltcad.swingtree.common.Basic_UI_Exception_Spec$__spock_feature_0_0prov0_closure3@67fb2e8e","com.globaltcad.swingtree.common.Basic_UI_Exception_Spec$__spock_feature_0_0prov0_closure4@766fc0eb","com.globaltcad.swingtree.common.Basic_UI_Exception_Spec$__spock_feature_0_0prov0_closure5@72facc87","com.globaltcad.swingtree.common.Basic_UI_Exception_Spec$__spock_feature_0_0prov0_closure6@79662c9d","com.globaltcad.swingtree.common.Basic_UI_Exception_Spec$__spock_feature_0_0prov0_closure7@52d5d0fa","com.globaltcad.swingtree.common.Basic_UI_Exception_Spec$__spock_feature_0_0prov0_closure8@13c73001","com.globaltcad.swingtree.common.Basic_UI_Exception_Spec$__spock_feature_0_0prov0_closure9@df35143","com.globaltcad.swingtree.common.Basic_UI_Exception_Spec$__spock_feature_0_0prov0_closure10@14bef773","com.globaltcad.swingtree.common.Basic_UI_Exception_Spec$__spock_feature_0_0prov0_closure11@2719c61b","com.globaltcad.swingtree.common.Basic_UI_Exception_Spec$__spock_feature_0_0prov0_closure12@66f218d9","com.globaltcad.swingtree.common.Basic_UI_Exception_Spec$__spock_feature_0_0prov0_closure13@ca4134","com.globaltcad.swingtree.common.Basic_UI_Exception_Spec$__spock_feature_0_0prov0_closure14@50a97cd4","com.globaltcad.swingtree.common.Basic_UI_Exception_Spec$__spock_feature_0_0prov0_closure15@38d0f027","com.globaltcad.swingtree.common.Basic_UI_Exception_Spec$__spock_feature_0_0prov0_closure16@3d72a1b6","com.globaltcad.swingtree.common.Basic_UI_Exception_Spec$__spock_feature_0_0prov0_closure17@34a0c416","com.globaltcad.swingtree.common.Basic_UI_Exception_Spec$__spock_feature_0_0prov0_closure18@7a9bd234","com.globaltcad.swingtree.common.Basic_UI_Exception_Spec$__spock_feature_0_0prov0_closure19@7398afad","com.globaltcad.swingtree.common.Basic_UI_Exception_Spec$__spock_feature_0_0prov0_closure20@6fa71b87","com.globaltcad.swingtree.common.Basic_UI_Exception_Spec$__spock_feature_0_0prov0_closure21@4ad20de0","com.globaltcad.swingtree.common.Basic_UI_Exception_Spec$__spock_feature_0_0prov0_closure22@1da2e315","com.globaltcad.swingtree.common.Basic_UI_Exception_Spec$__spock_feature_0_0prov0_closure23@d179138","com.globaltcad.swingtree.common.Basic_UI_Exception_Spec$__spock_feature_0_0prov0_closure24@5b27f4b2","com.globaltcad.swingtree.common.Basic_UI_Exception_Spec$__spock_feature_0_0prov0_closure25@5167a446","com.globaltcad.swingtree.common.Basic_UI_Exception_Spec$__spock_feature_0_0prov0_closure26@2ac69a54","com.globaltcad.swingtree.common.Basic_UI_Exception_Spec$__spock_feature_0_0prov0_closure27@150147ea","com.globaltcad.swingtree.common.Basic_UI_Exception_Spec$__spock_feature_0_0prov0_closure28@37ae4d25","com.globaltcad.swingtree.common.Basic_UI_Exception_Spec$__spock_feature_0_0prov0_closure29@3ca46432","com.globaltcad.swingtree.common.Basic_UI_Exception_Spec$__spock_feature_0_0prov0_closure30@2924d51d","com.globaltcad.swingtree.common.Basic_UI_Exception_Spec$__spock_feature_0_0prov0_closure31@3f7fdced","com.globaltcad.swingtree.common.Basic_UI_Exception_Spec$__spock_feature_0_0prov0_closure32@6272940f","com.globaltcad.swingtree.common.Basic_UI_Exception_Spec$__spock_feature_0_0prov0_closure33@f4e8663","com.globaltcad.swingtree.common.Basic_UI_Exception_Spec$__spock_feature_0_0prov0_closure34@63425c45","com.globaltcad.swingtree.common.Basic_UI_Exception_Spec$__spock_feature_0_0prov0_closure35@132e58e6","com.globaltcad.swingtree.common.Basic_UI_Exception_Spec$__spock_feature_0_0prov0_closure36@2fe4d3ec","com.globaltcad.swingtree.common.Basic_UI_Exception_Spec$__spock_feature_0_0prov0_closure37@15676332","com.globaltcad.swingtree.common.Basic_UI_Exception_Spec$__spock_feature_0_0prov0_closure38@30695d7a","com.globaltcad.swingtree.common.Basic_UI_Exception_Spec$__spock_feature_0_0prov0_closure39@53b42ca2","com.globaltcad.swingtree.common.Basic_UI_Exception_Spec$__spock_feature_0_0prov0_closure40@1826df18","com.globaltcad.swingtree.common.Basic_UI_Exception_Spec$__spock_feature_0_0prov0_closure41@32cffd96","com.globaltcad.swingtree.common.Basic_UI_Exception_Spec$__spock_feature_0_0prov0_closure42@890694c","com.globaltcad.swingtree.common.Basic_UI_Exception_Spec$__spock_feature_0_0prov0_closure43@65f21fa3","com.globaltcad.swingtree.common.Basic_UI_Exception_Spec$__spock_feature_0_0prov0_closure44@4d845811","com.globaltcad.swingtree.common.Basic_UI_Exception_Spec$__spock_feature_0_0prov0_closure45@1929fe80","com.globaltcad.swingtree.common.Basic_UI_Exception_Spec$__spock_feature_0_0prov0_closure46@7265f620","com.globaltcad.swingtree.common.Basic_UI_Exception_Spec$__spock_feature_0_0prov0_closure47@595b147"]}}
      ],
      "problems":{"dataValues":[], "errors":[]}
    }
  
  ],
  "generator":"https://github.com/renatoathaydes/spock-reports"
}